MANIFEST.in
setup.py
ftn_jsd.egg-info/PKG-INFO
ftn_jsd.egg-info/SOURCES.txt
ftn_jsd.egg-info/dependency_links.txt
ftn_jsd.egg-info/not-zip-safe
ftn_jsd.egg-info/requires.txt
ftn_jsd.egg-info/top_level.txt
src/generated/__init__.py
src/generated/base_generator.py
src/generated/execute.py
src/generated/generate.py
src/generated/generate_django.py
src/generated/generate_play.py
src/generated/root.py
src/generated/model/model.tx
src/generated/model/test.rbt
src/generated/templates/django_templates/apps/t__init__.tx
src/generated/templates/django_templates/apps/tsettings.tx
src/generated/templates/django_templates/apps/turls.tx
src/generated/templates/django_templates/apps/tviews.tx
src/generated/templates/django_templates/apps/twsgi.tx
src/generated/templates/django_templates/assets/css/bootstrap-custom.css
src/generated/templates/django_templates/assets/css/bootstrap-custom.min.css
src/generated/templates/django_templates/assets/css/main.css
src/generated/templates/django_templates/assets/fonts/LigatureSymbols/LigatureSymbols-2.11.eot
src/generated/templates/django_templates/assets/fonts/LigatureSymbols/LigatureSymbols-2.11.otf
src/generated/templates/django_templates/assets/fonts/LigatureSymbols/LigatureSymbols-2.11.svg
src/generated/templates/django_templates/assets/fonts/LigatureSymbols/LigatureSymbols-2.11.ttf
src/generated/templates/django_templates/assets/fonts/LigatureSymbols/LigatureSymbols-2.11.woff
src/generated/templates/django_templates/assets/fonts/LigatureSymbols/README.txt
src/generated/templates/django_templates/assets/fonts/LigatureSymbols/index.html
src/generated/templates/django_templates/assets/fonts/LigatureSymbols/style.css
src/generated/templates/django_templates/assets/img/django-pony.png
src/generated/templates/django_templates/assets/img/docker-logo.png
src/generated/templates/django_templates/assets/img/docker-top-logo.png
src/generated/templates/django_templates/assets/img/footer-links.png
src/generated/templates/django_templates/assets/img/github_small.png
src/generated/templates/django_templates/assets/img/glyphicons-halflings-white.png
src/generated/templates/django_templates/assets/img/glyphicons-halflings.png
