Metadata-Version: 1.0
Name: ftn-jsd
Version: 1.0
Summary: Generate some Django and Play code
Home-page: https://github.com/ftn-tim2/jsd-project.git
Author: FTN
Author-email: ftn@ftn.com
License: MIT
Platform: UNKNOWN
